setup.py
probability_distributions/Binomialdistribution.py
probability_distributions/Gaussiandistribution.py
probability_distributions/Generaldistribution.py
probability_distributions/__init__.py
probability_distributions.egg-info/PKG-INFO
probability_distributions.egg-info/SOURCES.txt
probability_distributions.egg-info/dependency_links.txt
probability_distributions.egg-info/not-zip-safe
probability_distributions.egg-info/top_level.txt