Metadata-Version: 1.0
Name: probability-distributions
Version: 0.5
Summary: Probability Distributions
Home-page: UNKNOWN
Author: Samsay
Author-email: samsayalam4@gmail.com
License: UNKNOWN
Platform: UNKNOWN
